README.rst
hmac_cli.py
setup.py
hmac_cli.egg-info/PKG-INFO
hmac_cli.egg-info/SOURCES.txt
hmac_cli.egg-info/dependency_links.txt
hmac_cli.egg-info/entry_points.txt
hmac_cli.egg-info/not-zip-safe
hmac_cli.egg-info/requires.txt
hmac_cli.egg-info/top_level.txt