Metadata-Version: 1.1
Name: hmac-cli
Version: 0.0.0
Summary: Simple CLI for encrypting data with a private key, using HMAC
Home-page: https://github.com/msabramo/hmac_cli
Author: Marc Abramowitz
Author-email: msabramo@gmail.com
License: MIT
Keywords: hmac
Platform: UNKNOWN
Classifier: Programming Language :: Python :: 2
Classifier: Programming Language :: Python :: 2.6
Classifier: Programming Language :: Python :: 2.7
Classifier: Programming Language :: Python :: 3
Classifier: Programming Language :: Python :: 3.2
Classifier: Programming Language :: Python :: 3.3
Classifier: Programming Language :: Python :: 3.4
Classifier: Topic :: Software Development :: Testing
Classifier: Natural Language :: English
Classifier: Intended Audience :: Developers
